AUTHORS.md
CHANGELOG.md
LICENSE
MANIFEST.in
README.md
requirements.txt
setup.py
datalogy/__init__.py
datalogy/html.py
datalogy/sample.py
datalogy/scrape.py
datalogy/util.py
datalogy.egg-info/PKG-INFO
datalogy.egg-info/SOURCES.txt
datalogy.egg-info/dependency_links.txt
datalogy.egg-info/entry_points.txt
datalogy.egg-info/requires.txt
datalogy.egg-info/top_level.txt