Metadata-Version: 1.0
Name: datalogy
Version: 0.1.0
Summary: A collection of command-line tools that facilitate the obtaining, scrubbing
Home-page: https://github.com/michaeljoseph/datalogy
Author: UNKNOWN
Author-email: UNKNOWN
License: UNKNOWN
Platform: UNKNOWN
